fl_classifier/__init__.py
fl_classifier/fl-classifier.py
fl_classifier-0.1.0.dist-info/licenses/LICENSE
fl_classifier-0.1.0.dist-info/METADATA
fl_classifier-0.1.0.dist-info/WHEEL
fl_classifier-0.1.0.dist-info/entry_points.txt
fl_classifier-0.1.0.dist-info/top_level.txt
fl_classifier-0.1.0.dist-info/RECORD
