Metadata-Version: 2.4
Name: fl-classifier
Version: 0.1.0
Summary: A tool to automatically classify files based on extension or timestamp
Author-email: Brian Adi <maill.brianadi@gmail.com>
License: MIT
Project-URL: Homepage, https://github.com/bri-anadi/fl-classifier
Project-URL: Bug Tracker, https://github.com/bri-anadi/fl-classifier/issues
Keywords: file,organization,classification
Classifier: Programming Language :: Python :: 3
Classifier: License :: OSI Approved :: MIT License
Classifier: Operating System :: OS Independent
Requires-Python: >=3.6
License-File: LICENSE
Dynamic: license-file
